x_yahw_x/__init__.py
x_yahw_x/x_yahw_x.py
x_yahw_x-10.0.0.dist-info/METADATA
x_yahw_x-10.0.0.dist-info/WHEEL
x_yahw_x-10.0.0.dist-info/top_level.txt
x_yahw_x-10.0.0.dist-info/RECORD
