Metadata-Version: 2.4
Name: x_yahw_x
Version: 10.0.0
Summary: Really simple 'Yet Another Hello World' package.
Author-email: Roy GM <eye4357@outlook.com>
License-Expression: MIT
